devtale/__init__.py
devtale/aggregators/__init__.py
devtale/aggregators/go.py
devtale/aggregators/javascript.py
devtale/aggregators/php.py
devtale/aggregators/python.py
devtale/cli.py
devtale/constants.py
devtale/schema.py
devtale/templates.py
devtale/utils.py
devtale-0.1.4.dist-info/LICENSE
devtale-0.1.4.dist-info/METADATA
devtale-0.1.4.dist-info/WHEEL
devtale-0.1.4.dist-info/entry_points.txt
devtale-0.1.4.dist-info/RECORD
