Metadata-Version: 2.1
Name: devtale
Version: 0.1.4
Summary: Generate automatic repository documentation with LLMs
Home-page: https://github.com/mystral-ai/devtale
License: MIT
Author: Mystral AI
Requires-Python: >=3.11.4,<4.0.0
Classifier: License :: OSI Approved :: MIT License
Classifier: Programming Language :: Python :: 3
Classifier: Programming Language :: Python :: 3.12
Requires-Dist: click (>=8.1.6,<9.0.0)
Requires-Dist: json-repair (>=0.4.5,<0.5.0)
Requires-Dist: langchain (>=0.0.251,<0.0.252)
Requires-Dist: openai (>=0.27.8,<0.28.0)
Requires-Dist: python-dotenv (>=1.0.0,<2.0.0)
Requires-Dist: tiktoken (>=0.5.1,<0.6.0)
Project-URL: Repository, https://github.com/mystral-ai/devtale
